manga_dl/__init__.py
manga_dl/app.py
manga_dl/main.py
manga_dl/manga.py
manga_dl/manga_sources/__init__.py
manga_dl/manga_sources/base_source.py
manga_dl/manga_sources/source1.py
manga_dl/manga_sources/source2.py
manga_dl/manga_sources/utils.py
manga_dl/public/bootstrap530.css
manga_dl/public/bootstrap530.js
manga_dl/public/error.png
manga_dl/public/jquery321.js
manga_dl/public/loading-fast.gif
manga_dl/public/manga.js
manga_dl/public/search.js
manga_dl/public/style.css
manga_dl/templates/chapter.html
manga_dl/templates/layout.html
manga_dl/templates/manga.html
manga_dl/templates/search.html
manga_dl/tools/__init__.py
manga_dl/tools/create_pdf.py
manga_dl/tools/download.py
manga_dl/tools/downloader2.py
manga_dl/tools/downloader3.py
manga_dl/tools/exceptions.py
manga_dl/tools/flask_cloudflared.py
manga_dl/tools/models.py
manga_dl/tools/utils.py
RapidMangaDL-0.2.7.dist-info/LICENSE
RapidMangaDL-0.2.7.dist-info/METADATA
RapidMangaDL-0.2.7.dist-info/WHEEL
RapidMangaDL-0.2.7.dist-info/entry_points.txt
RapidMangaDL-0.2.7.dist-info/top_level.txt
RapidMangaDL-0.2.7.dist-info/RECORD
