Metadata-Version: 2.1
Name: RapidMangaDL
Version: 0.2.7
Summary: Swiftly download manga from multiple sources.
Home-page: https://github.com/shhossain/RapidMangaDL
Author: sifat
Author-email: hossain0338@gmail.com
License: MIT
Project-URL: Documentation, https://github.com/shhossain/RapidMangaDL
Project-URL: Issue Tracker, https://github.com/shhossain/RapidMangaDL/issues
Project-URL: Source Code, https://github.com/shhossain/RapidMangaDL
Keywords: manga downloader
Classifier: Development Status :: 3 - Alpha
Classifier: Environment :: Console
Classifier: Environment :: Web Environment
Classifier: Intended Audience :: End Users/Desktop
Classifier: Intended Audience :: Developers
Classifier: Intended Audience :: Information Technology
Classifier: License :: OSI Approved :: MIT License
Classifier: Natural Language :: English
Classifier: Operating System :: OS Independent
Classifier: Topic :: Internet :: WWW/HTTP :: Dynamic Content
Classifier: Topic :: Internet :: WWW/HTTP :: WSGI :: Application
Classifier: Topic :: Software Development :: Libraries :: Application Frameworks
Classifier: Topic :: Software Development :: Libraries :: Python Modules
Classifier: Topic :: Software Development :: User Interfaces
Classifier: Topic :: Software Development :: Widget Sets
Classifier: Topic :: Utilities
Requires-Python: >=3.6
License-File: LICENSE
Requires-Dist: reportlab (>=4.0.4)
Requires-Dist: img2pdf (>=0.4.0)
Requires-Dist: PyPDF2 (>=3.0.1)
Requires-Dist: pillow
Requires-Dist: fake-headers
Requires-Dist: aiofiles
Requires-Dist: tqdm
Requires-Dist: aiohttp
Requires-Dist: BeautifulSoup4
Requires-Dist: colorama
Requires-Dist: flask
Requires-Dist: ebooklib
Requires-Dist: fuzzywuzzy
Requires-Dist: questionary
Requires-Dist: cloudscraper (>=1.2.71)
Requires-Dist: python-Levenshtein (==0.21.1)
Requires-Dist: nest-asyncio
Requires-Dist: pytimedinput (>=2.0.1)
Requires-Dist: selenium (>=4.0.0)
Requires-Dist: chromedriver-autoinstaller (>=0.4.1)
Requires-Dist: Brotli (>=1.0.9)
